rw_banks/__init__.py
rw_banks-0.0.4.dist-info/DESCRIPTION.rst
rw_banks-0.0.4.dist-info/METADATA
rw_banks-0.0.4.dist-info/RECORD
rw_banks-0.0.4.dist-info/WHEEL
rw_banks-0.0.4.dist-info/metadata.json
rw_banks-0.0.4.dist-info/top_level.txt
test/__init__.py
