Metadata-Version: 2.0
Name: rw-banks
Version: 0.0.4
Summary: Get a list of licensed banks from Rwanda and their corresponding swift code, address, contact info, ussd code and bank code
Home-page: UNKNOWN
Author: Igwaneza Bruce
Author-email: knowbeeinc@gmail.com
License: MIT
Keywords: banks,rwanda,banki
Platform: UNKNOWN
Classifier: Programming Language :: Python
Classifier: Programming Language :: Python :: 3.8
Classifier: Programming Language :: Python :: 3.7
Classifier: Programming Language :: Python :: 3.6
Classifier: Programming Language :: Python :: 3.5
Classifier: Programming Language :: Python :: 3.4
Classifier: Programming Language :: Python :: 3.3
Classifier: Programming Language :: Python :: 3.2
Classifier: Programming Language :: Python :: 3.1
Classifier: Programming Language :: Python :: 3.0
Classifier: Programming Language :: Python :: 2.7
Classifier: Intended Audience :: Developers
Classifier: Intended Audience :: Education
Classifier: Operating System :: OS Independent
Requires-Python: >=3.6
